toon_parser/__init__.py
toon_parser/parser.py
toon_format_parser-1.1.0.dist-info/METADATA
toon_format_parser-1.1.0.dist-info/WHEEL
toon_format_parser-1.1.0.dist-info/top_level.txt
toon_format_parser-1.1.0.dist-info/RECORD
