Metadata-Version: 2.4
Name: toon-format-parser
Version: 1.1.0
Summary: Token-Oriented Object Notation (TOON) parser for Python
Author-email: John Paez <johnpaez@tuprofedeia.com.co>
Project-URL: Homepage, https://github.com/johpaz/toon-parser-py
Classifier: Programming Language :: Python :: 3
Classifier: License :: OSI Approved :: MIT License
Classifier: Operating System :: OS Independent
Requires-Python: >=3.7
